hotmart_python/__init__.py
hotmart_python/decorators.py
hotmart_python/hotmart.py
hotmart_python-0.5.0.dist-info/LICENSE.txt
hotmart_python-0.5.0.dist-info/METADATA
hotmart_python-0.5.0.dist-info/WHEEL
hotmart_python-0.5.0.dist-info/RECORD
