Metadata-Version: 2.1
Name: hotmart-python
Version: 0.5.0
Summary: A Python library for the Hotmart API, simplifying endpoint access and resource management.
License: Apache License, Version 2.0
Author: Matheus Tenório
Author-email: matheusct16@gmail.com
Requires-Python: >=3.9,<4.0
Classifier: License :: Other/Proprietary License
Classifier: Programming Language :: Python :: 3
Classifier: Programming Language :: Python :: 3.9
Classifier: Programming Language :: Python :: 3.10
Classifier: Programming Language :: Python :: 3.11
Classifier: Programming Language :: Python :: 3.12
Requires-Dist: coloredlogs (>=15.0.1,<16.0.0)
Requires-Dist: requests (>=2.31.0,<3.0.0)
